odoo/addons/purchase_request/README.rst
odoo/addons/purchase_request/__init__.py
odoo/addons/purchase_request/__manifest__.py
odoo/addons/purchase_request/data/purchase_request_data.xml
odoo/addons/purchase_request/data/purchase_request_sequence.xml
odoo/addons/purchase_request/demo/purchase_request_demo.xml
odoo/addons/purchase_request/i18n/am.po
odoo/addons/purchase_request/i18n/ar.po
odoo/addons/purchase_request/i18n/bg.po
odoo/addons/purchase_request/i18n/bs.po
odoo/addons/purchase_request/i18n/ca.po
odoo/addons/purchase_request/i18n/ca_ES.po
odoo/addons/purchase_request/i18n/cs.po
odoo/addons/purchase_request/i18n/da.po
odoo/addons/purchase_request/i18n/de.po
odoo/addons/purchase_request/i18n/el_GR.po
odoo/addons/purchase_request/i18n/en_GB.po
odoo/addons/purchase_request/i18n/es.po
odoo/addons/purchase_request/i18n/es_AR.po
odoo/addons/purchase_request/i18n/es_CO.po
odoo/addons/purchase_request/i18n/es_CR.po
odoo/addons/purchase_request/i18n/es_DO.po
odoo/addons/purchase_request/i18n/es_EC.po
odoo/addons/purchase_request/i18n/es_ES.po
odoo/addons/purchase_request/i18n/es_MX.po
odoo/addons/purchase_request/i18n/es_PE.po
odoo/addons/purchase_request/i18n/es_PY.po
odoo/addons/purchase_request/i18n/es_VE.po
odoo/addons/purchase_request/i18n/et.po
odoo/addons/purchase_request/i18n/eu.po
odoo/addons/purchase_request/i18n/fa.po
odoo/addons/purchase_request/i18n/fi.po
odoo/addons/purchase_request/i18n/fr.po
odoo/addons/purchase_request/i18n/fr_BE.po
odoo/addons/purchase_request/i18n/fr_CA.po
odoo/addons/purchase_request/i18n/fr_CH.po
odoo/addons/purchase_request/i18n/fr_FR.po
odoo/addons/purchase_request/i18n/gl.po
odoo/addons/purchase_request/i18n/gl_ES.po
odoo/addons/purchase_request/i18n/he.po
odoo/addons/purchase_request/i18n/hr.po
odoo/addons/purchase_request/i18n/hr_HR.po
odoo/addons/purchase_request/i18n/hu.po
odoo/addons/purchase_request/i18n/id.po
odoo/addons/purchase_request/i18n/it.po
odoo/addons/purchase_request/i18n/ja.po
odoo14_addon_purchase_request-14.0.2.2.1.dist-info/METADATA
odoo14_addon_purchase_request-14.0.2.2.1.dist-info/WHEEL
odoo14_addon_purchase_request-14.0.2.2.1.dist-info/top_level.txt
odoo14_addon_purchase_request-14.0.2.2.1.dist-info/RECORD
